setup.py
gbdf_probability/Binomialdistribution.py
gbdf_probability/Gaussiandistribution.py
gbdf_probability/Generaldistribution.py
gbdf_probability/__init__.py
gbdf_probability.egg-info/PKG-INFO
gbdf_probability.egg-info/SOURCES.txt
gbdf_probability.egg-info/dependency_links.txt
gbdf_probability.egg-info/not-zip-safe
gbdf_probability.egg-info/top_level.txt